libgrav_sim.so
grav_sim/__init__.py
grav_sim/__main__.py
grav_sim/api.py
grav_sim/parameters.py
grav_sim/plotting.py
grav_sim/simulator.py
grav_sim/system.py
grav_sim/utils.py
grav_sim-1.0.0.dist-info/METADATA
grav_sim-1.0.0.dist-info/WHEEL
grav_sim-1.0.0.dist-info/top_level.txt
grav_sim-1.0.0.dist-info/RECORD
grav_sim-1.0.0.dist-info/licenses/LICENSE
