Metadata-Version: 2.4
Name: grav_sim
Version: 1.0.0
Summary: Gravity Simulator
Author-email: Ching-Yin Ng <alvinng324@gmail.com>
Requires-Python: >=3.9
License-File: LICENSE
Requires-Dist: matplotlib>=3.8.3
Requires-Dist: numpy>=1.26.4
Requires-Dist: h5py>=3.0.0
Requires-Dist: cmake>=3.10.0
Provides-Extra: dev
Requires-Dist: ruff; extra == "dev"
Requires-Dist: pytest; extra == "dev"
Dynamic: license-file
